nba_drafted/__init__.py
nba_drafted/build_features.py
nba_drafted/make_dataset.py
nba_drafted/predict_model.py
nba_drafted/train_model.py
nba_drafted/visulaize.py
nba_drafted-0.1.0.dist-info/METADATA
nba_drafted-0.1.0.dist-info/WHEEL
nba_drafted-0.1.0.dist-info/top_level.txt
nba_drafted-0.1.0.dist-info/RECORD
